models/__init__.py
models/message.py
Agent_Function_Calling-0.2.2.dist-info/METADATA
Agent_Function_Calling-0.2.2.dist-info/WHEEL
Agent_Function_Calling-0.2.2.dist-info/entry_points.txt
Agent_Function_Calling-0.2.2.dist-info/top_level.txt
Agent_Function_Calling-0.2.2.dist-info/RECORD
