Metadata-Version: 2.1
Name: Agent-Function-Calling
Version: 0.2.2
Summary: A tool to easily integrate custom functions with OpenAI's GPT models.
Author: Thierry Mayrand
Author-email: thierry.mayrand.ads@gmail.com
License: MIT
Classifier: Development Status :: 3 - Alpha
Classifier: Intended Audience :: Developers
Classifier: Topic :: Software Development :: Libraries
Classifier: License :: OSI Approved :: MIT License
Classifier: Programming Language :: Python :: 3
Classifier: Programming Language :: Python :: 3.6
Classifier: Programming Language :: Python :: 3.7
Classifier: Programming Language :: Python :: 3.8
Classifier: Programming Language :: Python :: 3.9
Requires-Dist: openai
Requires-Dist: python-dotenv
Requires-Dist: PyYAML
